arrow_pd_parser/__init__.py
arrow_pd_parser/_arrow_parsers.py
arrow_pd_parser/_export.py
arrow_pd_parser/_readers.py
arrow_pd_parser/_writers.py
arrow_pd_parser/caster.py
arrow_pd_parser/pa_pd.py
arrow_pd_parser/reader.py
arrow_pd_parser/utils.py
arrow_pd_parser/writer.py
arrow_pd_parser-2.2.0.dist-info/LICENCE.md
arrow_pd_parser-2.2.0.dist-info/METADATA
arrow_pd_parser-2.2.0.dist-info/WHEEL
arrow_pd_parser-2.2.0.dist-info/RECORD
