Metadata-Version: 2.1
Name: arrow_pd_parser
Version: 2.2.0
Summary: MoJ arrow-pd-parser
Home-page: https://github.com/moj-analytical-services/mojap-arrow-pd-parser
Author: Karik Isichei
Author-email: karik.isichei@digital.justice.gov.uk
Requires-Python: >=3.8,<4.0
Classifier: Programming Language :: Python :: 3
Classifier: Programming Language :: Python :: 3.8
Classifier: Programming Language :: Python :: 3.9
Classifier: Programming Language :: Python :: 3.10
Classifier: Programming Language :: Python :: 3.11
Classifier: Programming Language :: Python :: 3.12
Requires-Dist: awswrangler (>=2.4.0)
Requires-Dist: mojap-metadata[arrow] (>=1.10.0,<2.0.0)
Requires-Dist: pandas (>=1.2)
Requires-Dist: pyarrow (>=14.0.0)
Requires-Dist: smart-open (>=5.2.1,<6.0.0)
Project-URL: Repository, https://github.com/moj-analytical-services/mojap-arrow-pd-parser
